LICENSE
README.md
pyproject.toml
setup.py
ib_core_lite/__init__.py
ib_core_lite/helpers.py
ib_core_lite/settings.py
ib_core_lite/utils.py
ib_core_lite.egg-info/PKG-INFO
ib_core_lite.egg-info/SOURCES.txt
ib_core_lite.egg-info/dependency_links.txt
ib_core_lite.egg-info/requires.txt
ib_core_lite.egg-info/top_level.txt
ib_core_lite/authorization/__init__.py
ib_core_lite/authorization/models.py
ib_core_lite/authorization/types.py
ib_core_lite/authorization/utils.py
ib_core_lite/logging/__init__.py
ib_core_lite/logging/utils.py
ib_core_lite/types/__init__.py