Metadata-Version: 2.1
Name: ib-core-lite
Version: 1.0.1
Summary: Integration Bus fastapi-applications core
Home-page: https://gitlab.it-psg.com/ib-elp-it-psg/ib_core_lite
Download-URL: https://gitlab.it-psg.com/ib-elp-it-psg/ib_core_lite.git
Author: Damir Fatkhullin
Author-email: damir.f@it-psg.com
License: MIT
Classifier: License :: OSI Approved :: MIT License
Classifier: Programming Language :: Python :: 2.7
Classifier: Programming Language :: Python :: 3.4
Classifier: Programming Language :: Python :: 3.5
License-File: LICENSE
Requires-Dist: fastapi
Requires-Dist: starlette
Requires-Dist: requests
